djangocms_themata/__init__.py
djangocms_themata/admin.py
djangocms_themata/apps.py
djangocms_themata/management/commands/importbootswatch.py
djangocms_themata/migrations/0001_initial.py
djangocms_themata/migrations/0002_auto_20250113_1849.py
djangocms_themata/migrations/__init__.py
djangocms_themata/models.py
djangocms_themata/templates/base.html
djangocms_themata/templates/themata/link.html
djangocms_themata/templates/themata/navbar copy.html
djangocms_themata/templates/themata/navbar.html
djangocms_themata/templates/themata/pagination.html
djangocms_themata/templatetags/themata.py
djangocms_themata/util.py
djangocms_themata-0.1.2.dist-info/METADATA
djangocms_themata-0.1.2.dist-info/WHEEL
djangocms_themata-0.1.2.dist-info/RECORD
